CHANGELOG.rst
LICENSE
MANIFEST.in
README.md
requirements.txt
requirements_test.txt
run_tests.sh
setup.cfg
setup.py
prometheus/__init__.py
prometheus/collectors.py
prometheus/exporter.py
prometheus/formats.py
prometheus/metricdict.py
prometheus/negotiator.py
prometheus/pusher.py
prometheus/registry.py
prometheus/test_collectors.py
prometheus/test_exporter.py
prometheus/test_formats.py
prometheus/test_metricdict.py
prometheus/test_negotiator.py
prometheus/test_pusher.py
prometheus/test_registry.py
prometheus/test_utils.py
prometheus/utils.py
prometheus.egg-info/PKG-INFO
prometheus.egg-info/SOURCES.txt
prometheus.egg-info/dependency_links.txt
prometheus.egg-info/not-zip-safe
prometheus.egg-info/requires.txt
prometheus.egg-info/top_level.txt
prometheus/pb2/metrics_pb2.py