Metadata-Version: 1.1
Name: prometheus
Version: 0.3.0
Summary: Python Prometheus client
Home-page: https://github.com/slok/prometheus-python
Author: Xabier Larrakoetxea
Author-email: slok69@gmail.com
License: MIT License
Download-URL: https://github.com/slok/prometheus-python/tarball/0.3.0
Keywords: prometheus,client,metrics
Platform: UNKNOWN
Classifier: Development Status :: 3 - Alpha
Classifier: Intended Audience :: Developers
Classifier: Natural Language :: English
Classifier: License :: OSI Approved :: MIT License
Classifier: Programming Language :: Python
Classifier: Programming Language :: Python :: 3
Classifier: Programming Language :: Python :: 3.3
Classifier: Programming Language :: Python :: 3.4
